img2csv/__init__.py
img2csv/img2csv.py
img2csv-0.1.0.dist-info/LICENSE
img2csv-0.1.0.dist-info/METADATA
img2csv-0.1.0.dist-info/WHEEL
img2csv-0.1.0.dist-info/entry_points.txt
img2csv-0.1.0.dist-info/top_level.txt
img2csv-0.1.0.dist-info/RECORD
