Metadata-Version: 2.1
Name: img2csv
Version: 0.1.0
Summary: A package to convert images paths to CSV
Home-page: https://github.com/MJBioInfo/img2csv
Author: Dr.Majeed Jamakhani
Author-email: mjbioinfo@gmail.com
Classifier: Programming Language :: Python :: 3
Classifier: License :: OSI Approved :: MIT License
Classifier: Operating System :: OS Independent
Requires-Python: >=3.6
License-File: LICENSE
Requires-Dist: pandas
